aliyunsdkmarket/__init__.py
aliyunsdkmarket/endpoint.py
aliyunsdkmarket/request/__init__.py
aliyunsdkmarket/request/v20151101/ActivateLicenseRequest.py
aliyunsdkmarket/request/v20151101/AutoRenewInstanceRequest.py
aliyunsdkmarket/request/v20151101/CreateOrderRequest.py
aliyunsdkmarket/request/v20151101/CrossAccountVerifyTokenRequest.py
aliyunsdkmarket/request/v20151101/DescribeApiMeteringRequest.py
aliyunsdkmarket/request/v20151101/DescribeCurrentNodeInfoRequest.py
aliyunsdkmarket/request/v20151101/DescribeDistributionProductsLinkRequest.py
aliyunsdkmarket/request/v20151101/DescribeDistributionProductsRequest.py
aliyunsdkmarket/request/v20151101/DescribeInstanceForIsvRequest.py
aliyunsdkmarket/request/v20151101/DescribeInstanceRequest.py
aliyunsdkmarket/request/v20151101/DescribeInstancesRequest.py
aliyunsdkmarket/request/v20151101/DescribeLicenseRequest.py
aliyunsdkmarket/request/v20151101/DescribeOrderForIsvRequest.py
aliyunsdkmarket/request/v20151101/DescribeOrderRequest.py
aliyunsdkmarket/request/v20151101/DescribePriceRequest.py
aliyunsdkmarket/request/v20151101/DescribeProductRequest.py
aliyunsdkmarket/request/v20151101/DescribeProductsRequest.py
aliyunsdkmarket/request/v20151101/DescribeProjectAttachmentsRequest.py
aliyunsdkmarket/request/v20151101/DescribeProjectInfoRequest.py
aliyunsdkmarket/request/v20151101/DescribeProjectMessagesRequest.py
aliyunsdkmarket/request/v20151101/DescribeProjectNodesRequest.py
aliyunsdkmarket/request/v20151101/DescribeProjectOperateLogsRequest.py
aliyunsdkmarket/request/v20151101/FinishCurrentProjectNodeRequest.py
aliyunsdkmarket/request/v20151101/PauseProjectRequest.py
aliyunsdkmarket/request/v20151101/PushMeteringDataRequest.py
aliyunsdkmarket/request/v20151101/ResumeProjectRequest.py
aliyunsdkmarket/request/v20151101/RollbackCurrentProjectNodeRequest.py
aliyunsdkmarket/request/v20151101/__init__.py
aliyun_python_sdk_market-1.0.6.dist-info/LICENSE
aliyun_python_sdk_market-1.0.6.dist-info/METADATA
aliyun_python_sdk_market-1.0.6.dist-info/WHEEL
aliyun_python_sdk_market-1.0.6.dist-info/top_level.txt
aliyun_python_sdk_market-1.0.6.dist-info/RECORD
